sparse_list.py
sparse_list-1.0.dist-info/LICENSE.txt
sparse_list-1.0.dist-info/METADATA
sparse_list-1.0.dist-info/WHEEL
sparse_list-1.0.dist-info/top_level.txt
sparse_list-1.0.dist-info/RECORD
