Metadata-Version: 2.1
Name: sparse-list
Version: 1.0
Summary: A list where most values will be None (or some other default)
Home-page: https://github.com/johnsyweb/python_sparse_list
Author: Pete Johns
Author-email: paj+pypi@johnsy.com
Maintainer: Pete Johns
Maintainer-email: paj+pypi@johnsy.com
License: MIT
Download-URL: https://github.com/johnsyweb/python_sparse_list/tarball/1.0
Keywords: sparse,list,container,iterable
Platform: UNKNOWN
Classifier: Development Status :: 4 - Beta
Classifier: Intended Audience :: Developers
Classifier: License :: OSI Approved :: MIT License
Classifier: Operating System :: OS Independent
Classifier: Programming Language :: Python
Classifier: Programming Language :: Python :: 3
Classifier: Programming Language :: Python :: 3.6
Classifier: Programming Language :: Python :: 3.7
Classifier: Programming Language :: Python :: 3.8
Classifier: Programming Language :: Python :: 3.9
Classifier: Programming Language :: Python :: Implementation :: CPython
Classifier: Programming Language :: Python :: Implementation :: PyPy
Classifier: Topic :: Software Development
Classifier: Topic :: Software Development :: Libraries
Classifier: Topic :: Software Development :: Libraries :: Python Modules
Classifier: Topic :: Utilities
